solarspatialtools/__init__.py
solarspatialtools/cmv.py
solarspatialtools/field.py
solarspatialtools/irradiance.py
solarspatialtools/signalproc.py
solarspatialtools/spatial.py
solarspatialtools/stats.py
solarspatialtools/dataio/__init__.py
solarspatialtools/dataio/hope_campaign.py
solarspatialtools/dataio/iotools.py
solarspatialtools/dataio/nrcan_data.py
solarspatialtools/synthirrad/__init__.py
solarspatialtools/synthirrad/cloudfield.py
solarspatialtools/visualization/__init__.py
solarspatialtools/visualization/vis_tools.py
solarspatialtools-0.5.1.dist-info/LICENSE
solarspatialtools-0.5.1.dist-info/METADATA
solarspatialtools-0.5.1.dist-info/WHEEL
solarspatialtools-0.5.1.dist-info/top_level.txt
solarspatialtools-0.5.1.dist-info/RECORD
