Metadata-Version: 2.1
Name: solarspatialtools
Version: 0.5.1
Summary: A package for spatial analysis of solar energy and solar irradiance
Home-page: https://github.com/jranalli/solarspatialtools
Author: 'Joe Ranalli'
Author-email: jar339@psu.edu
Project-URL: Bug Tracker, https://github.com/jranalli/solarspatialtools/issues
Project-URL: Documentation, https://solarspatialtools.readthedocs.io
Classifier: Programming Language :: Python :: 3
Classifier: License :: OSI Approved :: BSD License
Classifier: Operating System :: OS Independent
Classifier: Topic :: Scientific/Engineering
Classifier: Intended Audience :: Science/Research
License-File: LICENSE
Requires-Dist: numpy
Requires-Dist: pandas
Requires-Dist: tables
Requires-Dist: pyproj
Requires-Dist: pvlib
Requires-Dist: netcdf4
Requires-Dist: scipy
Requires-Dist: matplotlib
Provides-Extra: demos
Requires-Dist: jupyter ; extra == 'demos'
Provides-Extra: docs
Requires-Dist: sphinx ==7.4.7 ; extra == 'docs'
Requires-Dist: sphinx-rtd-theme ==2.0.0 ; extra == 'docs'
Requires-Dist: nbsphinx ==0.9.5 ; extra == 'docs'
Requires-Dist: ipython ==8.27.0 ; extra == 'docs'
Requires-Dist: nbsphinx-link ==1.3.0 ; extra == 'docs'
Provides-Extra: tests
Requires-Dist: pytest ; extra == 'tests'
